supernet_duo/__init__.py
supernet_duo/core.py
supernet_duo-0.1.7.dist-info/licenses/LICENSE
supernet_duo-0.1.7.dist-info/METADATA
supernet_duo-0.1.7.dist-info/WHEEL
supernet_duo-0.1.7.dist-info/top_level.txt
supernet_duo-0.1.7.dist-info/RECORD
