Metadata-Version: 2.4
Name: supernet_duo
Version: 0.1.7
Summary: Supernet_Duo: A extremley quick and simple neural network classifier, and prediction model now with option to return class or percent sure of that class when using the classifier.
Author-email: Bodhi <bodhishanbhag@gmail.com>
License: MIT License
Requires-Python: >=3.8
License-File: LICENSE
Dynamic: license-file
